LICENSE
MANIFEST.in
README.md
setup.py
carefree_creator.egg-info/PKG-INFO
carefree_creator.egg-info/SOURCES.txt
carefree_creator.egg-info/dependency_links.txt
carefree_creator.egg-info/entry_points.txt
carefree_creator.egg-info/requires.txt
carefree_creator.egg-info/top_level.txt
cfcreator/__init__.py
cfcreator/cli.py
cfcreator/common.py
cfcreator/control.py
cfcreator/control_multi.py
cfcreator/cos.py
cfcreator/cv.py
cfcreator/endpoints.py
cfcreator/img2img.py
cfcreator/img2txt.py
cfcreator/parameters.py
cfcreator/pipeline.py
cfcreator/txt2img.py
cfcreator/txt2txt.py
cfcreator/upscale.py
cfcreator/utils.py
cfcreator/workflow.py
cfcreator/apis/config.yml
cfcreator/apis/interface.py
cfcreator/apis/kafka/config.yml
cfcreator/apis/kafka/consumer.py
cfcreator/apis/kafka/producer.py
cfcreator/legacy/__init__.py
cfcreator/legacy/common.py
cfcreator/legacy/control.py
cfcreator/legacy/control_multi.py
cfcreator/sdks/__init__.py
cfcreator/sdks/apis.py
cfcreator/sdks/direct.py
cfcreator/sdks/kafka.py
cfcreator/sdks/utils.py
cfcreator/third_party/__init__.py
cfcreator/third_party/facexlib.py
tests/test.py
tests/test_kafka.py
tests/test_workflow.py