Metadata-Version: 2.1
Name: carefree-creator
Version: 0.2.10
Summary: An AI-powered creator for everyone.
Author: carefree0910
Author-email: syameimaru.saki@gmail.com
Keywords: python carefree-learn PyTorch
Provides-Extra: kafka
Provides-Extra: third_party
Provides-Extra: full
License-File: LICENSE
